LICENSE
MANIFEST.in
NOTICE
README.md
requirements-dev.txt
requirements.txt
setup.py
vwo/__init__.py
vwo/vwo.py
vwo/vwo_builder.py
vwo/vwo_client.py
vwo/api/__init__.py
vwo/api/get_flag_api.py
vwo/api/set_attribute_api.py
vwo/api/track_api.py
vwo/constants/Constants.py
vwo/constants/__init__.py
vwo/decorators/__init__.py
vwo/decorators/storage_decorator.py
vwo/enums/__init__.py
vwo/enums/api_enum.py
vwo/enums/campaign_type_enum.py
vwo/enums/debug_category_enum.py
vwo/enums/event_enum.py
vwo/enums/headers_enum.py
vwo/enums/hooks_enum.py
vwo/enums/status_enum.py
vwo/enums/storage_enum.py
vwo/enums/url_enum.py
vwo/models/Alias.py
vwo/models/AliasSetResponse.py
vwo/models/__init__.py
vwo/models/batch_event_data.py
vwo/models/gateway_service_model.py
vwo/models/vwo_options_model.py
vwo/models/campaign/__init__.py
vwo/models/campaign/campaign_model.py
vwo/models/campaign/feature_model.py
vwo/models/campaign/impact_campaign_model.py
vwo/models/campaign/metric_model.py
vwo/models/campaign/rule_model.py
vwo/models/campaign/variable_model.py
vwo/models/campaign/variation_model.py
vwo/models/schemas/__init__.py
vwo/models/schemas/campaign_group_schema.py
vwo/models/schemas/campaign_metric_schema.py
vwo/models/schemas/campaign_schema.py
vwo/models/schemas/campaign_variation_schema.py
vwo/models/schemas/empty_object_schema.py
vwo/models/schemas/feature_schema.py
vwo/models/schemas/group_schema.py
vwo/models/schemas/rule_schema.py
vwo/models/schemas/settings_schema.py
vwo/models/schemas/variable_schema.py
vwo/models/settings/__init__.py
vwo/models/settings/settings_model.py
vwo/models/storage/__init__.py
vwo/models/storage/storage_model.py
vwo/models/user/__init__.py
vwo/models/user/context_model.py
vwo/models/user/context_vwo_model.py
vwo/models/user/get_flag.py
vwo/packages/__init__.py
vwo/packages/decision_maker/__init__.py
vwo/packages/decision_maker/decision_maker.py
vwo/packages/logger/__init__.py
vwo/packages/logger/log_message_builder.py
vwo/packages/logger/logger.py
vwo_fme_python_sdk.egg-info/PKG-INFO
vwo_fme_python_sdk.egg-info/SOURCES.txt
vwo_fme_python_sdk.egg-info/dependency_links.txt
vwo_fme_python_sdk.egg-info/requires.txt
vwo_fme_python_sdk.egg-info/top_level.txt