Metadata-Version: 2.1
Name: vwo-fme-python-sdk
Version: 1.16.0
Summary: VWO Feature Management and Experimentation SDK for Python
Home-page: https://github.com/wingify/vwo-fme-python-sdk
Author: VWO
Author-email: dev@wingify.com
License: Apache License 2.0
Classifier: Development Status :: 5 - Production/Stable
Classifier: Environment :: Web Environment
Classifier: Intended Audience :: Developers
Classifier: License :: OSI Approved :: Apache Software License
Classifier: Operating System :: OS Independent
Classifier: Programming Language :: Python
Classifier: Programming Language :: Python :: 3.6
Classifier: Programming Language :: Python :: 3.7
Classifier: Programming Language :: Python :: 3.8
Classifier: Programming Language :: Python :: 3.9
Classifier: Programming Language :: Python :: 3.10
Classifier: Programming Language :: Python :: 3.11
License-File: LICENSE
License-File: NOTICE
Requires-Dist: murmurhash==1.0.10
Requires-Dist: requests>=2.27.1
Requires-Dist: jsonschema>=3.2.0
